hermes_mail/__about__.py
hermes_mail/__init__.py
hermes_mail/_src/hermes_mail.py
hermes_mail-0.1.1.dist-info/METADATA
hermes_mail-0.1.1.dist-info/WHEEL
hermes_mail-0.1.1.dist-info/licenses/LICENSE
hermes_mail-0.1.1.dist-info/RECORD
