Metadata-Version: 2.1
Name: hermes-mail
Version: 0.1.1
Summary: Send Python job alerts via email
Project-URL: Homepage, https://github.com/ishan0102/hermes-mail
Project-URL: Bug Tracker, https://github.com/ishan0102/hermes-mail/issues
Author-email: Ishan Shah <ishan0102@utexas.edu>
License-Expression: MIT
License-File: LICENSE
Classifier: License :: OSI Approved :: MIT License
Classifier: Operating System :: OS Independent
Classifier: Programming Language :: Python :: 3
Requires-Python: >=3
